jaskier/__init__.py
jaskier-0.1.0.post1.dist-info/WHEEL
jaskier-0.1.0.post1.dist-info/METADATA
jaskier-0.1.0.post1.dist-info/RECORD
