Metadata-Version: 2.1
Name: jaskier
Version: 0.1.0.post1
Summary: 
License: MIT
Author: Bartek Sokorski
Author-email: b.sokorski@gmail.com
Requires-Python: >=3.7,<3.12
Classifier: License :: OSI Approved :: MIT License
Classifier: Programming Language :: Python :: 3
Classifier: Programming Language :: Python :: 3.7
Classifier: Programming Language :: Python :: 3.8
Classifier: Programming Language :: Python :: 3.9
Classifier: Programming Language :: Python :: 3.10
Requires-Dist: jinja2 (>=3.1.2,<4.0.0)
Requires-Dist: tomli (>=2.0.1,<3.0.0); python_version < "3.11"
